pkgNipun/__init__.py
pkgNipun-1.1.6.2.dist-info/LICENSE.txt
pkgNipun-1.1.6.2.dist-info/METADATA
pkgNipun-1.1.6.2.dist-info/WHEEL
pkgNipun-1.1.6.2.dist-info/top_level.txt
pkgNipun-1.1.6.2.dist-info/RECORD
