Metadata-Version: 2.1
Name: pkgNipun
Version: 1.1.6.2
Summary: sample description
Author: Nipun Dogra
Classifier: Programming Language :: Python :: 3
Classifier: License :: OSI Approved :: MIT License
Classifier: Operating System :: OS Independent
Requires-Python: >=3.6
License-File: LICENSE.txt
